reskin_sensor/__init__.py
reskin_sensor/sensor.py
reskin_sensor/sensor_proc.py
reskin_sensor-2.0.1.dist-info/LICENSE
reskin_sensor-2.0.1.dist-info/METADATA
reskin_sensor-2.0.1.dist-info/WHEEL
reskin_sensor-2.0.1.dist-info/top_level.txt
reskin_sensor-2.0.1.dist-info/RECORD
