Metadata-Version: 2.1
Name: reskin-sensor
Version: 2.0.1
Summary: Data acquisition library for a ReSkin sensor
Home-page: https://github.com/raunaqbhirangi/reskin_sensor.git
Author: Raunaq Bhirangi
Author-email: rbhirang@andrew.cmu.edu
Requires-Python: >=3.6
License-File: LICENSE
Requires-Dist: numpy (>=1.21.3)
Requires-Dist: pyserial (>=3.5)
